setup.py
hezbutions/Binomialdistribution.py
hezbutions/Gaussiandistribution.py
hezbutions/Generaldistribution.py
hezbutions/__init__.py
hezbutions.egg-info/PKG-INFO
hezbutions.egg-info/SOURCES.txt
hezbutions.egg-info/dependency_links.txt
hezbutions.egg-info/not-zip-safe
hezbutions.egg-info/top_level.txt